vaultio/__init__.py
vaultio/scripts/build.py
vaultio/scripts/cli.py
vaultio/util.py
vaultio/vault/__init__.py
vaultio/vault/api.py
vaultio/vault/debug_decrypt.py
vaultio/vault/schema.py
vaultio/vault/server.py
vaultio/vault/vault_cli.py
vaultio/vault/vault_rbw.py
vaultio/vault/vault_server.py
vaultio/vault/vault_sync.py
vaultio_examples/backup.py
vaultio_examples/copy_org.py
vaultio_examples/shell.py
vaultio_examples/sync.py
vaultio-0.2.121.dist-info/LICENSE
vaultio-0.2.121.dist-info/METADATA
vaultio-0.2.121.dist-info/WHEEL
vaultio-0.2.121.dist-info/entry_points.txt
vaultio-0.2.121.dist-info/RECORD
