Metadata-Version: 2.3
Name: vaultio
Version: 0.2.121
Summary: Unofficial tool for stateless Bitwarden vault management
License: GPL-3.0-or-later
Author: Patrick Lenihan
Author-email: patrick@plenihan.com
Requires-Python: >=3.13
Classifier: License :: OSI Approved :: GNU General Public License v3 or later (GPLv3+)
Classifier: Programming Language :: Python :: 3
Classifier: Programming Language :: Python :: 3.13
Requires-Dist: argon2-cffi (>=23.1.0,<24.0.0)
Requires-Dist: cryptography (>=44.0.2,<45.0.0)
Requires-Dist: fire (>=0.7.0,<0.8.0)
Requires-Dist: nodeenv (>=1.9.1,<2.0.0)
Requires-Dist: psutil (>=7.0.0,<8.0.0)
Requires-Dist: requests (>=2.32.3,<3.0.0)
Requires-Dist: requests-toolbelt (>=1.0.0,<2.0.0)
Requires-Dist: rich (>=14.0.0,<15.0.0)
